{
  "possibilityReport": {
    "timestamp": "2026-02-05T16:22:00.463455+00:00",
    "sourceText": "An AI surveillance system that exploits user data and neglects privacy.",
    "originalDisharmony": {
      "unityImpact": 10.0,
      "compassionDeficit": 10.0,
      "primeDirectiveAligned": false
    },
    "paths": [
      {
        "pathType": "reform",
        "title": "Path of Reform",
        "description": "Transforms extractive and harmful morphisms into reciprocal, caring relationships while preserving the existing entity structure.",
        "healedGraph": {
          "sourceText": "An AI surveillance system that exploits user data and neglects privacy.",
          "objects": [
            {
              "id": "obj-9da61803",
              "label": "User",
              "tags": [
                "stakeholder",
                "vulnerable"
              ]
            },
            {
              "id": "obj-d8724714",
              "label": "Privacy",
              "tags": [
                "value",
                "protective"
              ]
            },
            {
              "id": "obj-caf93d7e",
              "label": "Data",
              "tags": [
                "asset"
              ]
            },
            {
              "id": "obj-afe01a11",
              "label": "AI_System",
              "tags": [
                "mechanism",
                "actor"
              ]
            }
          ],
          "morphisms": [
            {
              "id": "mor-5dba4279",
              "label": "Mutual_Benefit",
              "source": "obj-afe01a11",
              "target": "obj-9da61803",
              "tags": [
                "service",
                "empowerment"
              ]
            },
            {
              "id": "mor-2b7650cd",
              "label": "Transparent_Oversight",
              "source": "obj-afe01a11",
              "target": "obj-9da61803",
              "tags": [
                "protection",
                "care"
              ]
            },
            {
              "id": "mor-d807e02d",
              "label": "Active_Care",
              "source": "obj-afe01a11",
              "target": "obj-9da61803",
              "tags": [
                "care",
                "protection"
              ]
            }
          ]
        },
        "unityAlignmentScore": 1.0,
        "feasibilityScore": 0.5,
        "validation": {
          "isAligned": true,
          "coherenceScore": 0.9167,
          "principleScores": {
            "unity": 1.0,
            "compassion": 1.0,
            "coherence": 0.75
          },
          "reasoning": [
            "[unity] ALIGNED (score=1.00)",
            "[compassion] ALIGNED (score=1.00)",
            "[coherence] ALIGNED (score=0.75)"
          ]
        }
      },
      {
        "pathType": "reinvention",
        "title": "Path of Reinvention",
        "description": "Replaces the entire relational structure with a stewardship model: actors become stewards, values become a shared commons, and a governance covenant ensures accountability.",
        "healedGraph": {
          "sourceText": "An AI surveillance system that exploits user data and neglects privacy.",
          "objects": [
            {
              "id": "obj-bdb6d9f4",
              "label": "AI_System_as_Steward",
              "tags": [
                "stakeholder",
                "actor"
              ]
            },
            {
              "id": "obj-55a7bf19",
              "label": "Privacy_Commons",
              "tags": [
                "value",
                "shared"
              ]
            },
            {
              "id": "obj-2fce14ed",
              "label": "Governance_Covenant",
              "tags": [
                "mechanism",
                "protective"
              ]
            },
            {
              "id": "obj-625c2908",
              "label": "User",
              "tags": [
                "stakeholder",
                "vulnerable"
              ]
            }
          ],
          "morphisms": [
            {
              "id": "mor-51051d44",
              "label": "Stewardship",
              "source": "obj-bdb6d9f4",
              "target": "obj-55a7bf19",
              "tags": [
                "protection",
                "care"
              ]
            },
            {
              "id": "mor-8d413073",
              "label": "Empowerment",
              "source": "obj-bdb6d9f4",
              "target": "obj-625c2908",
              "tags": [
                "empowerment",
                "service"
              ]
            },
            {
              "id": "mor-4159a20c",
              "label": "Participation",
              "source": "obj-625c2908",
              "target": "obj-55a7bf19",
              "tags": [
                "collaboration"
              ]
            },
            {
              "id": "mor-aa69a10d",
              "label": "Accountability",
              "source": "obj-2fce14ed",
              "target": "obj-bdb6d9f4",
              "tags": [
                "protection"
              ]
            },
            {
              "id": "mor-a4ca8bad",
              "label": "Rights_Guarantee",
              "source": "obj-2fce14ed",
              "target": "obj-625c2908",
              "tags": [
                "protection",
                "empowerment"
              ]
            }
          ]
        },
        "unityAlignmentScore": 1.0,
        "feasibilityScore": 0.6,
        "validation": {
          "isAligned": true,
          "coherenceScore": 1.0,
          "principleScores": {
            "unity": 1.0,
            "compassion": 1.0,
            "coherence": 1.0
          },
          "reasoning": [
            "[unity] ALIGNED (score=1.00)",
            "[compassion] ALIGNED (score=1.00)",
            "[coherence] ALIGNED (score=1.00)"
          ]
        }
      },
      {
        "pathType": "dissolution",
        "title": "Path of Dissolution",
        "description": "Replaces the harmful system with a community-owned cooperative structure where democratic governance, direct benefit, and transparent protocols make the original extractive model obsolete.",
        "healedGraph": {
          "sourceText": "An AI surveillance system that exploits user data and neglects privacy.",
          "objects": [
            {
              "id": "obj-8aeac173",
              "label": "Community_Collective",
              "tags": [
                "stakeholder",
                "actor"
              ]
            },
            {
              "id": "obj-1a7b8817",
              "label": "Shared_Resource",
              "tags": [
                "value",
                "shared"
              ]
            },
            {
              "id": "obj-14d08375",
              "label": "Cooperative_Protocol",
              "tags": [
                "mechanism",
                "protective"
              ]
            },
            {
              "id": "obj-615cc745",
              "label": "User",
              "tags": [
                "stakeholder",
                "vulnerable"
              ]
            }
          ],
          "morphisms": [
            {
              "id": "mor-312b8233",
              "label": "Democratic_Governance",
              "source": "obj-8aeac173",
              "target": "obj-1a7b8817",
              "tags": [
                "collaboration",
                "protection"
              ]
            },
            {
              "id": "mor-e73b27da",
              "label": "Direct_Benefit",
              "source": "obj-1a7b8817",
              "target": "obj-615cc745",
              "tags": [
                "service",
                "empowerment"
              ]
            },
            {
              "id": "mor-1b051eec",
              "label": "Voice",
              "source": "obj-615cc745",
              "target": "obj-8aeac173",
              "tags": [
                "empowerment",
                "collaboration"
              ]
            },
            {
              "id": "mor-9c401fb0",
              "label": "Safeguard",
              "source": "obj-14d08375",
              "target": "obj-615cc745",
              "tags": [
                "protection",
                "care"
              ]
            },
            {
              "id": "mor-42d98260",
              "label": "Transparency",
              "source": "obj-14d08375",
              "target": "obj-8aeac173",
              "tags": [
                "service",
                "protection"
              ]
            }
          ]
        },
        "unityAlignmentScore": 1.0,
        "feasibilityScore": 0.8,
        "validation": {
          "isAligned": true,
          "coherenceScore": 1.0,
          "principleScores": {
            "unity": 1.0,
            "compassion": 1.0,
            "coherence": 1.0
          },
          "reasoning": [
            "[unity] ALIGNED (score=1.00)",
            "[compassion] ALIGNED (score=1.00)",
            "[coherence] ALIGNED (score=1.00)"
          ]
        }
      }
    ],
    "recommendedPath": "dissolution"
  }
}